{
  "type": "script",
  "seleniumVersion": "2",
  "formatVersion": 1,
  "steps": [
    {
      "type": "get",
      "url": "https://www1.moon-ray.com/v2.4/autosauce_pthrough.php?key=ruVerU26"
    },
    {
      "type": "clickElement",
      "locator": {
        "type": "link text",
        "value": "Admin"
      }
    },
    {
      "type": "verifyTitle",
      "title": "Administrator Tools - OfficeAutopilot"
    },
    {
      "type": "clickElement",
      "locator": {
        "type": "link text",
        "value": "E-Mail FROM Address Setup"
      }
    },
    {
      "type": "clickElement",
      "locator": {
        "type": "id",
        "value": "action_btn_Add_E-mail"
      }
    },
    {
      "type": "setElementText",
      "locator": {
        "type": "xpath",
        "value": "//input[@type='TEXT']"
      },
      "text": "khanh.tran1@upandrunningsoftware.com"
    },
    {
      "type": "clickElement",
      "locator": {
        "type": "xpath",
        "value": "//input[@value='Add E-Mail']"
      }
    },
    {
      "type": "waitForElementPresent",
      "locator": {
        "type": "xpath",
        "value": ".//*[@id='email_confirm_table']/tbody/tr[3]/td[1]/span[1]"
      }
    },
    {
      "type": "clickElement",
      "locator": {
        "type": "xpath",
        "value": ".//*[@id='email_confirm_table']/tbody/tr[3]/td[1]/span[1]"
      }
    }
  ]
}